browser_use/__init__.py
browser_use/exceptions.py
browser_use/logging_config.py
browser_use/utils.py
browser_use/agent/gif.py
browser_use/agent/prompts.py
browser_use/agent/service.py
browser_use/agent/system_prompt.md
browser_use/agent/views.py
browser_use/agent/memory/__init__.py
browser_use/agent/memory/service.py
browser_use/agent/message_manager/service.py
browser_use/agent/message_manager/utils.py
browser_use/agent/message_manager/views.py
browser_use/browser/browser.py
browser_use/browser/chrome.py
browser_use/browser/context.py
browser_use/browser/dolphin_service.py
browser_use/browser/views.py
browser_use/browser/utils/screen_resolution.py
browser_use/controller/service.py
browser_use/controller/views.py
browser_use/controller/registry/service.py
browser_use/controller/registry/views.py
browser_use/dom/__init__.py
browser_use/dom/buildDomTree.js
browser_use/dom/service.py
browser_use/dom/views.py
browser_use/dom/clickable_element_processor/service.py
browser_use/dom/history_tree_processor/service.py
browser_use/dom/history_tree_processor/view.py
browser_use/telemetry/service.py
browser_use/telemetry/views.py
tn_browser_use-0.1.44.dist-info/METADATA
tn_browser_use-0.1.44.dist-info/WHEEL
tn_browser_use-0.1.44.dist-info/licenses/LICENSE
tn_browser_use-0.1.44.dist-info/RECORD
