Metadata-Version: 2.4
Name: tn-browser-use
Version: 0.1.44
Summary: Make websites accessible for AI agents
Project-URL: Repository, https://github.com/browser-use/browser-use
Author: Gregor Zunic, Sourabha
License-File: LICENSE
Classifier: License :: OSI Approved :: MIT License
Classifier: Operating System :: OS Independent
Classifier: Programming Language :: Python :: 3
Requires-Python: <4.0,>=3.11
Requires-Dist: botocore>=1.37.23
Requires-Dist: faiss-cpu>=1.10.0
Requires-Dist: google-api-core>=2.24.0
Requires-Dist: httpx>=0.27.2
Requires-Dist: langchain-anthropic==0.3.3
Requires-Dist: langchain-aws>=0.2.11
Requires-Dist: langchain-core==0.3.49
Requires-Dist: langchain-deepseek>=0.1.3
Requires-Dist: langchain-google-genai==2.1.2
Requires-Dist: langchain-ollama==0.3.0
Requires-Dist: langchain-openai==0.3.11
Requires-Dist: langchain>=0.3.21
Requires-Dist: markdownify==1.1.0
Requires-Dist: mem0ai==0.1.88
Requires-Dist: playwright>=1.51.0
Requires-Dist: posthog>=3.7.0
Requires-Dist: psutil>=7.0.0
Requires-Dist: pydantic<2.11.0,>=2.10.4
Requires-Dist: pyobjc>=11.0; platform_system == 'darwin'
Requires-Dist: pyperclip>=1.9.0
Requires-Dist: python-dotenv>=1.0.1
Requires-Dist: requests>=2.32.3
Requires-Dist: screeninfo>=0.8.1; platform_system != 'darwin'
Requires-Dist: sentence-transformers>=4.0.2
Requires-Dist: typing-extensions>=4.12.2
Provides-Extra: dev
Requires-Dist: build>=1.2.2; extra == 'dev'
Requires-Dist: codespell>=2.4.1; extra == 'dev'
Requires-Dist: fastapi>=0.115.8; extra == 'dev'
Requires-Dist: inngest>=0.4.19; extra == 'dev'
Requires-Dist: ipdb>=0.13.13; extra == 'dev'
Requires-Dist: langchain-fireworks>=0.2.6; extra == 'dev'
Requires-Dist: pre-commit>=4.2.0; extra == 'dev'
Requires-Dist: pytest-asyncio>=0.24.0; extra == 'dev'
Requires-Dist: pytest>=8.3.5; extra == 'dev'
Requires-Dist: ruff>=0.11.2; extra == 'dev'
Requires-Dist: tokencost>=0.1.16; extra == 'dev'
Requires-Dist: uvicorn>=0.34.0; extra == 'dev'
